recipely/__init__.py
recipely/site_generator.py
recipely-0.0.post845.dist-info/entry_points.txt
recipely-0.0.post845.dist-info/LICENSE
recipely-0.0.post845.dist-info/WHEEL
recipely-0.0.post845.dist-info/METADATA
recipely-0.0.post845.dist-info/RECORD
