Metadata-Version: 2.1
Name: recipely
Version: 0.0.post845
Summary: Initialisation module for recipely.
Home-page: https://github.com/martynvdijke/recipely
Author: Martyn van Dijke
Author-email: martijnvdijke600@gmail.com
Classifier: License :: OSI Approved :: MIT License
Requires-Dist: flit_core>=2.2.0
Requires-Dist: coloredlogs
Requires-Dist: python-frontmatter
Requires-Dist: jinja2
Requires-Dist: setuptools_scm
Requires-Dist: python-slugify
Requires-Dist: jinja_markdown
